laser/__init__.py
laser/ethereum/__init__.py
laser/ethereum/gascost.py
laser/ethereum/helper.py
laser/ethereum/svm.py
laser/ethereum/modules/__init__.py
mythril/__init__.py
mythril/exceptions.py
mythril/analysis/__init__.py
mythril/analysis/callgraph.py
mythril/analysis/ops.py
mythril/analysis/report.py
mythril/analysis/security.py
mythril/analysis/symbolic.py
mythril/analysis/modules/__init__.py
mythril/analysis/modules/delegatecall_forward.py
mythril/analysis/modules/ether_send.py
mythril/analysis/modules/unchecked_suicide.py
mythril/disassembler/__init__.py
mythril/disassembler/disassembly.py
mythril/disassembler/signatures.json
mythril/ether/__init__.py
mythril/ether/asm.py
mythril/ether/contractstorage.py
mythril/ether/ethcontract.py
mythril/ether/evm.py
mythril/ether/util.py
mythril/ipc/__init__.py
mythril/ipc/client.py
mythril/ipc/constants.py
mythril/ipc/exceptions.py
mythril/ipc/utils.py
mythril/rpc/__init__.py
mythril/rpc/client.py
mythril/rpc/constants.py
mythril/rpc/exceptions.py
mythril/rpc/utils.py
mythril/support/__init__.py
mythril/support/loader.py
mythril-0.8.0.data/scripts/myth
mythril-0.8.0.dist-info/DESCRIPTION.rst
mythril-0.8.0.dist-info/METADATA
mythril-0.8.0.dist-info/RECORD
mythril-0.8.0.dist-info/WHEEL
mythril-0.8.0.dist-info/metadata.json
mythril-0.8.0.dist-info/top_level.txt
