Metadata-Version: 2.0
Name: mythril
Version: 0.8.0
Summary: A reversing and bug hunting framework for the Ethereum blockchain
Home-page: https://github.com/b-mueller/mythril
Author: Bernhard Mueller
Author-email: bernhard.mueller11@gmail.com
License: MIT
Keywords: hacking disassembler security ethereum
Platform: UNKNOWN
Classifier: Development Status :: 3 - Alpha
Classifier: Intended Audience :: Science/Research
Classifier: Topic :: Software Development :: Disassemblers
Classifier: License :: OSI Approved :: MIT License
Classifier: Programming Language :: Python :: 2
Classifier: Programming Language :: Python :: 2.7
Classifier: Programming Language :: Python :: 3
Classifier: Programming Language :: Python :: 3.3
Classifier: Programming Language :: Python :: 3.4
Classifier: Programming Language :: Python :: 3.5
Requires-Python: >=3.5
Requires-Dist: BTrees
Requires-Dist: ZODB (>=5.3.0)
Requires-Dist: ethereum (>=2.0.4)
Requires-Dist: laser-ethereum (==0.2.9)
Requires-Dist: requests
Requires-Dist: web3
Requires-Dist: z3-solver (>=4.5)
